{
  "technologies": [
    {
      "id": "tech-001",
      "name": "Python",
      "type": "Programming Language",
      "category": "Backend/Scripting",
      "selfRating": 7,
      "proficiencyLevel": "Intermediate",
      "experienceYears": "1yr",
      "primaryUse": "Backend development and data structures",
      "isCurrentlyUsing": true,
      "projectsUsedIn": [],
      "relatedTechnologies": [],
      "ecosystem": "Python",
      "description": "Versatile programming for backend and automation",
      "portfolioDisplay": true,
      "displayOrder": 1,
      "tags": ["programming", "backend", "scripting","data-structures"],
      "imageUrl": "technologies/python"
    },
    {
      "id": "tech-002", 
      "name": "Java",
      "type": "Programming Language",
      "category": "Backend",
      "selfRating": 7,
      "proficiencyLevel": "Intermediate",
      "experienceYears": "1-2yrs",
      "primaryUse": "Object-oriented programming and enterprise applications",
      "isCurrentlyUsing": true,
      "projectsUsedIn": ["Ping Pong","Snake-Xenzia-Game","Turtle-Crossing-Game","Password Generator"],
      "relatedTechnologies": [],
      "ecosystem": "Java",
      "description": "Strong foundation in OOP and enterprise development",
      "portfolioDisplay": true,
      "displayOrder": 2,
      "tags": ["programming", "oop"],
      "imageUrl": "technologies/java"
    },
    {
      "id": "tech-003",
      "name": "C++",
      "type": "Programming Language", 
      "category":"data-structures",
      "selfRating": 6,
      "proficiencyLevel": "Intermediate",
      "experienceYears": "1-2yrs",
      "primaryUse": "System programming and competitive programming",
      "isCurrentlyUsing": false,
      "projectsUsedIn": [],
      "relatedTechnologies": ["C"],
      "ecosystem": "C/C++",
      "description": "Low-level programming and algorithm implementation",
      "portfolioDisplay": true,
      "displayOrder": 3,
      "tags": ["programming", "algorithms"],
      "imageUrl": "technologies/c++"
    },
    {
      "id": "tech-004",
      "name": "C",
      "type": "Programming Language",
      "category": "Systems Programming",
      "selfRating": 5,
      "proficiencyLevel": "Beginner",
      "experienceYears": "<6 months",
      "primaryUse": "Basic system programming and understanding fundamentals",
      "isCurrentlyUsing": false,
      "projectsUsedIn": [],
      "relatedTechnologies": ["C++"],
      "ecosystem": "C/C++",
      "description": "Foundation programming language knowledge",
      "portfolioDisplay": false,
      "displayOrder": 4,
      "tags": ["programming", "systems", "fundamentals"],
      "imageUrl": "technologies/c"
    },
    {
      "id": "tech-005",
      "name": "JavaScript",
      "type": "Programming Language",
      "category": "Web Development",
      "selfRating": 10,
      "proficiencyLevel": "Advanced",
      "experienceYears": "2-3yrs",
      "primaryUse": "Frontend and backend web development",
      "isCurrentlyUsing": true,
      "projectsUsedIn": ["Snap Map", "Order Up","Portfolio","To-Do-App","Akshay MindMap","DNOTES - Web3 Note-Taking Application"],
      "relatedTechnologies": ["TypeScript", "React", "Node.js"],
      "ecosystem": "JavaScript",
      "description": "Modern JavaScript for full-stack development",
      "portfolioDisplay": true,
      "displayOrder": 5,
      "tags": ["programming", "web", "frontend", "backend"],
      "imageUrl": "technologies/javascript"
    },
    {
      "id": "tech-006",
      "name": "TypeScript",
      "type": "Programming Language",
      "category": "Web Development",
      "selfRating": 7,
      "proficiencyLevel": "Intermediate",
      "experienceYears": "1-2yrs",
      "primaryUse": "Type-safe JavaScript development",
      "isCurrentlyUsing": true,
      "projectsUsedIn": ["Portfolio"],
      "relatedTechnologies": ["JavaScript", "React", "Node.js"],
      "ecosystem": "JavaScript",
      "description": "Strongly-typed JavaScript for robust applications",
      "portfolioDisplay": true,
      "displayOrder": 6,
      "tags": ["programming", "web", "typing"],
      "imageUrl": "technologies/typescript"
    },
    {
      "id": "tech-007",
      "name": "HTML",
      "type": "Programming Language",
      "category": "Frontend",
      "selfRating": 9,
      "proficiencyLevel": "Expert",
      "experienceYears": "3yrs",
      "primaryUse": "Web structure and markup",
      "isCurrentlyUsing": true,
      "projectsUsedIn": ["Snap Map", "Order Up","Portfolio","To-Do-App","Akshay MindMap","DNOTES - Web3 Note-Taking Application"],
      "relatedTechnologies": ["CSS", "JavaScript"],
      "ecosystem": "Web",
      "description": "Semantic HTML for accessible web structures",
      "portfolioDisplay": true,
      "displayOrder": 7,
      "tags": ["markup", "web", "frontend"],
      "imageUrl": "technologies/html"
    },
    {
      "id": "tech-008",
      "name": "CSS",
      "type": "Programming Language",
      "category": "Frontend",
      "selfRating": 8,
      "proficiencyLevel": "Advanced",
      "experienceYears": "2-3yrs",
      "primaryUse": "Web styling and responsive design",
      "isCurrentlyUsing": true,
      "projectsUsedIn": ["Snap Map", "Order Up","Portfolio","To-Do-App","Akshay MindMap","DNOTES - Web3 Note-Taking Application"],
      "relatedTechnologies": ["HTML", "Bootstrap"],
      "ecosystem": "Web",
      "description": "Modern CSS with Flexbox, Grid, and animations",
      "portfolioDisplay": true,
      "displayOrder": 8,
      "tags": ["styling", "web", "frontend", "responsive"],
      "imageUrl": "technologies/css"
    },
    {
      "id": "tech-009",
      "name": "Apex",
      "type": "Programming Language",
      "category": "Salesforce",
      "selfRating": 8,
      "proficiencyLevel": "Intermediate",
      "experienceYears": "6m-1yr",
      "primaryUse": "Salesforce custom development",
      "isCurrentlyUsing": true,
      "projectsUsedIn": [],
      "relatedTechnologies": ["Salesforce", "SOQL"],
      "ecosystem": "Salesforce",
      "description": "Salesforce platform development language",
      "portfolioDisplay": true,
      "displayOrder": 9,
      "tags": ["salesforce", "crm", "enterprise"],
      "imageUrl": "technologies/apex"
    },
    {
      "id": "tech-010",
      "name": "React",
      "type": "Library",
      "category": "Frontend",
      "selfRating": 9,
      "proficiencyLevel": "Advanced",
      "experienceYears": "2-3yrs",
      "primaryUse": "Building interactive user interfaces",
      "isCurrentlyUsing": true,
      "projectsUsedIn": [],
      "relatedTechnologies": ["JavaScript", "Next.js", "Material UI","HTML","CSS"],
      "ecosystem": "JavaScript",
      "description": "Modern React with hooks and context",
      "portfolioDisplay": true,
      "displayOrder": 10,
      "tags": ["library", "frontend", "ui", "spa"],
      "imageUrl": "technologies/react"
    },
    {
      "id": "tech-011",
      "name": "Next.js",
      "type": "Framework",
      "category": "Full-stack",
      "selfRating": 7,
      "proficiencyLevel": "Intermediate",
      "experienceYears": "1yr",
      "primaryUse": "Full-stack React applications with SSR",
      "isCurrentlyUsing": true,
      "projectsUsedIn": [],
      "relatedTechnologies": ["React", "JavaScript", "TypeScript"],
      "ecosystem": "JavaScript",
      "description": "Production-ready React framework",
      "portfolioDisplay": true,
      "displayOrder": 11,
      "tags": ["framework", "fullstack", "ssr", "react"],
      "imageUrl": "technologies/nextjs"
    },
    {
      "id": "tech-012",
      "name": "Node.js",
      "type": "Framework",
      "category": "Backend",
      "selfRating": 10,
      "proficiencyLevel": "Advanced",
      "experienceYears": "2-3yrs",
      "primaryUse": "Backend API development",
      "isCurrentlyUsing": true,
      "projectsUsedIn": [],
      "relatedTechnologies": ["JavaScript", "Express", "MongoDB"],
      "ecosystem": "JavaScript",
      "description": "Server-side JavaScript runtime",
      "portfolioDisplay": true,
      "displayOrder": 12,
      "tags": ["backend", "api", "server", "javascript"],
      "imageUrl": "technologies/nodejs"
    },
    {
      "id": "tech-013",
      "name": "Express",
      "type": "Framework",
      "category": "Backend",
      "selfRating": 8,
      "proficiencyLevel": "Intermediate",
      "experienceYears": "2-3yrs",
      "primaryUse": "RESTful API development",
      "isCurrentlyUsing": true,
      "projectsUsedIn": ["Snap Map"],
      "relatedTechnologies": ["Node.js", "MongoDB", "Mongoose"],
      "ecosystem": "JavaScript",
      "description": "Fast web framework for Node.js",
      "portfolioDisplay": true,
      "displayOrder": 13,
      "tags": ["framework", "backend", "api", "rest"],
      "imageUrl": "technologies/expressjs"
    },
    {
      "id": "tech-014",
      "name": "Mongoose",
      "type": "Library",
      "category": "Database",
      "selfRating": 7,
      "proficiencyLevel": "Intermediate",
      "experienceYears": "1-2yrs",
      "primaryUse": "MongoDB object modeling",
      "isCurrentlyUsing": true,
      "projectsUsedIn": ["Snap Map"],
      "relatedTechnologies": ["MongoDB", "Node.js", "Express"],
      "ecosystem": "JavaScript",
      "description": "Elegant MongoDB object modeling",
      "portfolioDisplay": true,
      "displayOrder": 14,
      "tags": ["library", "database", "mongodb", "orm"],
      "imageUrl": "technologies/mongoose"
    },
    {
      "id": "tech-015",
      "name": "EJS",
      "type": "Framework",
      "category": "Template Engine",
      "selfRating": 6,
      "proficiencyLevel": "Intermediate",
      "experienceYears": "6m-1yr",
      "primaryUse": "Server-side templating",
      "isCurrentlyUsing": false,
      "projectsUsedIn": [],
      "relatedTechnologies": ["Express", "Node.js"],
      "ecosystem": "JavaScript",
      "description": "Embedded JavaScript templating",
      "portfolioDisplay": false,
      "displayOrder": 15,
      "tags": ["template", "server", "ejs"],
      "imageUrl": "technologies/ejs"
    },
    {
      "id": "tech-016",
      "name": "Material UI",
      "type": "Library",
      "category": "UI Framework",
      "selfRating": 7,
      "proficiencyLevel": "Intermediate",
      "experienceYears": "1-2yrs",
      "primaryUse": "React component library for UI design",
      "isCurrentlyUsing": true,
      "projectsUsedIn": ["Snap Map"],
      "relatedTechnologies": ["React", "CSS", "JavaScript"],
      "ecosystem": "JavaScript",
      "description": "Google's Material Design for React",
      "portfolioDisplay": true,
      "displayOrder": 16,
      "tags": ["ui", "components", "design", "react"],
      "imageUrl": "technologies/material-ui"
    },
    {
      "id": "tech-017",
      "name": "Bootstrap",
      "type": "Framework",
      "category": "CSS Framework",
      "selfRating": 8,
      "proficiencyLevel": "Advanced",
      "experienceYears": "2-3yrs",
      "primaryUse": "Responsive web design",
      "isCurrentlyUsing": true,
      "projectsUsedIn": [],
      "relatedTechnologies": ["CSS", "HTML", "JavaScript"],
      "ecosystem": "Web",
      "description": "Popular CSS framework for responsive design",
      "portfolioDisplay": true,
      "displayOrder": 17,
      "tags": ["css", "framework", "responsive", "ui"],
      "imageUrl": "technologies/bootstrap"
    },
    {
      "id": "tech-018",
      "name": "jQuery",
      "type": "Library",
      "category": "JavaScript Library",
      "selfRating": 6,
      "proficiencyLevel": "Intermediate",
      "experienceYears": "1-2yrs",
      "primaryUse": "DOM manipulation and AJAX",
      "isCurrentlyUsing": false,
      "projectsUsedIn": [],
      "relatedTechnologies": ["JavaScript", "HTML", "CSS"],
      "ecosystem": "JavaScript",
      "description": "JavaScript library for DOM manipulation",
      "portfolioDisplay": false,
      "displayOrder": 18,
      "tags": ["library", "dom", "javascript", "legacy"],
      "imageUrl": "technologies/jquery"
    },
    {
      "id": "tech-019",
      "name": "MongoDB",
      "type": "Database",
      "category": "NoSQL Database",
      "selfRating": 8,
      "proficiencyLevel": "Advanced",
      "experienceYears": "2-3yrs",
      "primaryUse": "Document-based data storage",
      "isCurrentlyUsing": true,
      "projectsUsedIn": [],
      "relatedTechnologies": ["Mongoose", "Node.js", "Express"],
      "ecosystem": "NoSQL",
      "description": "Flexible NoSQL document database",
      "portfolioDisplay": true,
      "displayOrder": 19,
      "tags": ["database", "nosql", "document", "mongodb"],
      "imageUrl": "technologies/mongodb"
    },
    {
      "id": "tech-020",
      "name": "SQL",
      "type": "Database",
      "category": "Query Language",
      "selfRating": 7,
      "proficiencyLevel": "Intermediate",
      "experienceYears": "1-2yrs",
      "primaryUse": "Database querying and management",
      "isCurrentlyUsing": true,
      "projectsUsedIn": [],
      "relatedTechnologies": ["PostgreSQL", "MySQL", "Database Design"],
      "ecosystem": "SQL",
      "description": "Standard database query language",
      "portfolioDisplay": true,
      "displayOrder": 20,
      "tags": ["database", "query", "sql", "relational"],
      "imageUrl": "technologies/sql"
    },
    {
      "id": "tech-021",
      "name": "PostgreSQL",
      "type": "Database",
      "category": "Relational Database",
      "selfRating": 6,
      "proficiencyLevel": "Intermediate",
      "experienceYears": "6m-1yr",
      "primaryUse": "Advanced relational database operations",
      "isCurrentlyUsing": true,
      "projectsUsedIn": [],
      "relatedTechnologies": ["SQL", "Database Design"],
      "ecosystem": "SQL",
      "description": "Advanced open-source relational database",
      "portfolioDisplay": true,
      "displayOrder": 21,
      "tags": ["database", "postgresql", "relational", "advanced"],
      "imageUrl": "technologies/postgresql"
    },
    {
      "id": "tech-022",
      "name": "MySQL",
      "type": "Database",
      "category": "Relational Database",
      "selfRating": 6,
      "proficiencyLevel": "Intermediate",
      "experienceYears": "6m-1yr",
      "primaryUse": "Web application database backend",
      "isCurrentlyUsing": false,
      "projectsUsedIn": [],
      "relatedTechnologies": ["SQL", "PHP", "Web Development"],
      "ecosystem": "SQL",
      "description": "Popular open-source database system",
      "portfolioDisplay": true,
      "displayOrder": 22,
      "tags": ["database", "mysql", "relational", "web"],
      "imageUrl": "technologies/mysql"
    },
    {
      "id": "tech-023",
      "name": "Data Structures & Algorithms",
      "type": "Other",
      "category": "Computer Science",
      "selfRating": 7,
      "proficiencyLevel": "Intermediate",
      "experienceYears": "2-3yrs",
      "primaryUse": "Problem solving and efficient coding",
      "isCurrentlyUsing": true,
      "projectsUsedIn": [],
      "relatedTechnologies": ["Python", "Java", "C++"],
      "ecosystem": "Computer Science",
      "description": "Core computer science fundamentals",
      "portfolioDisplay": true,
      "displayOrder": 23,
      "tags": ["algorithms", "data-structures", "problem-solving", "cs"],
      "imageUrl": ""
    },
    {
      "id": "tech-024",
      "name": "Git",
      "type": "Tool",
      "category": "Version Control",
      "selfRating": 8,
      "proficiencyLevel": "Advanced",
      "experienceYears": "2-3yrs",
      "primaryUse": "Version control and collaboration",
      "isCurrentlyUsing": true,
      "projectsUsedIn": [],
      "relatedTechnologies": ["GitHub", "GitLab"],
      "ecosystem": "Development Tools",
      "description": "Distributed version control system",
      "portfolioDisplay": true,
      "displayOrder": 24,
      "tags": ["version-control", "git", "collaboration", "devtools"],
      "imageUrl": "technologies/git"
    },
    {
      "id": "tech-025",
      "name": "Blockchain",
      "type": "Other",
      "category": "Emerging Technology",
      "selfRating": 5,
      "proficiencyLevel": "Beginner",
      "experienceYears": "<6 months",
      "primaryUse": "Understanding decentralized systems",
      "isCurrentlyUsing": false,
      "projectsUsedIn": [],
      "relatedTechnologies": ["Cryptocurrency", "Smart Contracts"],
      "ecosystem": "Blockchain",
      "description": "Distributed ledger technology fundamentals",
      "portfolioDisplay": false,
      "displayOrder": 25,
      "tags": ["blockchain", "cryptocurrency", "decentralized"],
      "imageUrl": ""
    },
    {
      "id": "tech-026",
      "name": "CRM",
      "type": "Other",
      "category": "Business Systems",
      "selfRating": 6,
      "proficiencyLevel": "Intermediate",
      "experienceYears": "6m-1yr",
      "primaryUse": "Customer relationship management systems",
      "isCurrentlyUsing": true,
      "projectsUsedIn": [],
      "relatedTechnologies": ["Salesforce", "Business Process"],
      "ecosystem": "Business",
      "description": "Customer relationship management concepts",
      "portfolioDisplay": true,
      "displayOrder": 26,
      "tags": ["crm", "business", "customer-management"],
      "imageUrl": ""
    },
    {
      "id": "tech-027",
      "name": "Cloud",
      "type": "Other",
      "category": "Cloud Computing",
      "selfRating": 6,
      "proficiencyLevel": "Intermediate",
      "experienceYears": "6m-1yr",
      "primaryUse": "Cloud services and deployment",
      "isCurrentlyUsing": true,
      "projectsUsedIn": [],
      "relatedTechnologies": ["Deployment", "Salesforce"],
      "ecosystem": "Cloud",
      "description": "Cloud computing principles and services",
      "portfolioDisplay": true,
      "displayOrder": 27,
      "tags": ["cloud", "deployment", "scalability"],
      "imageUrl": ""
    },
    {
      "id": "tech-028",
      "name": "Salesforce",
      "type": "Other",
      "category": "CRM Platform",
      "selfRating": 7,
      "proficiencyLevel": "Intermediate",
      "experienceYears": "1yr",
      "primaryUse": "CRM development and customization",
      "isCurrentlyUsing": true,
      "projectsUsedIn": [],
      "relatedTechnologies": ["Apex", "Lightning", "SOQL"],
      "ecosystem": "Salesforce",
      "description": "Leading CRM platform development",
      "portfolioDisplay": true,
      "displayOrder": 28,
      "tags": ["salesforce", "crm", "platform", "enterprise"],
      "imageUrl": "technologies/salesforce"
    },
    {
      "id": "tech-029",
      "name": "SOQL",
      "type": "Query Language",
      "category": "Salesforce",
      "selfRating": 7,
      "proficiencyLevel": "Intermediate",
      "experienceYears": "6m-1yr",
      "primaryUse": "Salesforce data querying and retrieval",
      "isCurrentlyUsing": true,
      "projectsUsedIn": [],
      "relatedTechnologies": ["Salesforce", "Apex", "Database"],
      "ecosystem": "Salesforce",
      "description": "Salesforce Object Query Language for data operations",
      "portfolioDisplay": true,
      "displayOrder": 29,
      "tags": ["salesforce", "query", "database", "soql"],
      "imageUrl": "technologies/soql"
    }
  ]
}